icarus/__init__.py
icarus/create_moose_config.py
icarus/dataloader.py
icarus/datasets.py
icarus/model.py
icarus/sample_generator.py
icarus/utils.py
icarus/data/thermal_model_data.npz
icarus/data/thermal_monoblock_data.npz
icarus_fusion-0.1.2.dist-info/LICENSE
icarus_fusion-0.1.2.dist-info/METADATA
icarus_fusion-0.1.2.dist-info/WHEEL
icarus_fusion-0.1.2.dist-info/top_level.txt
icarus_fusion-0.1.2.dist-info/RECORD
