Metadata-Version: 2.1
Name: icarus-fusion
Version: 0.1.2
Summary: A machine learning tool for fusion simulation validation.
Author-email: arjavp-ukaea <arjav.poudel@ukaea.uk>, barisc-ukaea <baris.cavusoglu@ukaea.uk>, lukethehuman <luke.humphrey@ukaea.uk>
License: GNU GENERAL PUBLIC LICENSE
Project-URL: Repository, https://github.com/aurora-multiphysics/icarus
Project-URL: Issue Tracker, https://github.com/aurora-multiphysics/icarus/issues
Classifier: Programming Language :: Python :: 3
Classifier: License :: OSI Approved :: GNU General Public License v3 (GPLv3)
Classifier: Operating System :: OS Independent
Requires-Python: >=3.11
License-File: LICENSE
Requires-Dist: numpy >=1.26.0
Requires-Dist: netCDF4 >=1.6.5
Requires-Dist: scikit-learn >=1.5.0
Requires-Dist: scikit-optimize >=0.10.2
Requires-Dist: mooseherder >=0.1.0
Requires-Dist: matplotlib >=3.8.0
Requires-Dist: tqdm >=4.66.4
Requires-Dist: scipy ==1.11.3
